user_auth/__init__.py
user_auth/user_auth.py
user_auth-0.1.0.dist-info/LICENSE
user_auth-0.1.0.dist-info/METADATA
user_auth-0.1.0.dist-info/WHEEL
user_auth-0.1.0.dist-info/top_level.txt
user_auth-0.1.0.dist-info/RECORD
