Metadata-Version: 2.1
Name: user-auth
Version: 0.1.0
Summary: linux user-password authenticate
Home-page: https://github.com/William-ZXS/user-auth
Author: William-ZXS
Author-email: william_zxs@163.com
License: MIT
Platform: UNKNOWN
Classifier: License :: OSI Approved :: MIT License
Classifier: Programming Language :: Python
Classifier: Programming Language :: Python :: 2
Classifier: Programming Language :: Python :: 2.7
Classifier: Programming Language :: Python :: Implementation :: CPython
Classifier: Programming Language :: Python :: Implementation :: PyPy
Requires-Python: >=2.7.0
